README.md
setup.py
comm_ddp/comm.py
comm_ddp/demo.py
comm_ddp.egg-info/PKG-INFO
comm_ddp.egg-info/SOURCES.txt
comm_ddp.egg-info/dependency_links.txt
comm_ddp.egg-info/top_level.txt