Metadata-Version: 2.1
Name: comm-ddp
Version: 0.0.2
Summary: communication tools for pytorch-DDP
Author: Chaoyi Zhang
